{"cameraMode":{"drawMode":0,"name":"Shaded","section":"Shading Mode"},"sceneLighting":true,"audioPlay":false,"sceneViewState":{"m_AlwaysRefresh":false,"showFog":true,"showSkybox":true,"showFlares":true,"showImageEffects":true,"showParticleSystems":true,"showVisualEffectGraphs":true,"m_FxEnabled":true},"in2DMode":false,"pivot":{"x":7.23858118057251,"y":5.060107231140137,"z":-0.5891367793083191},"rotation":{"x":-0.2300664186477661,"y":0.7470311522483826,"z":-0.32157638669013979,"w":-0.5344387292861939},"size":2.9472296237945558,"orthographic":false}